{
  "name": "English SL I[A1]CS",
  "category": "実学基礎科目 外国語",
  "type": "演習科目",
  "code": "L601C01",
  "semester": "2026年度 前期",
  "date": "火 1",
  "target": "1年",
  "credit": "1.0",
  "room": "講義実験棟２０８",
  "teachers": [
    {
      "name": "石塚 美佳",
      "affiliation": "教養学環"
    }
  ],
  "updated_at": "2026-04-13T17:52:23.600031Z",
  "overview": "英語ネイティブスピーカーによる指導により、英語に触れる機会（インプット）を増やし、英語でやり取りを行うこと（アウトプット）によって、英語のコミュニケーション能力を向上させる。身近な話題に関する語彙力を養い、自分の考えを英語で表現できるように、様々なペアワークやグループワークによるタスクに取り組むことによってリスニング力、スピーキング力を向上させる。コミュニケーションを通して、指導者のもつ異なる文化的・社会的背景に触れ、関心をもち、英語を共通語として使用するグローバルな社会での考え方や振る舞い方についても学ぶ。 この授業では、道案内や観光での会話、人物の描写などを含め、毎回、異なる日常的なトピックを扱う。",
  "goal": "１．英語を用いてコミュニケーションをとることに対して臆せずに、自分の意志や意見を伝えようという態度をもつ。 ２．相手の話していることが聞き取れない場合でも、躊躇せずに聞き返したり、わからないという意思表示ができるようにする。 ３．グローバルな社会において、相手の文化や生活習慣、考え方に関心をもち、多様性を尊重できる。",
  "outcomes": "国際的な教養、コミュニケーション能力、論理的な思考力",
  "initiative": "アクティブラーニング",
  "way": "授業への参加と課題への取り組みが必要。授業は教科書や補助教材を使い、基本的に英語で行われ、会話練習にはペアワークやグループワークを多く取り入れる。日本語による私語は厳禁である。学生には、授業への英語による積極的な参加を求め、学生自らの主体的な学び（アクティブラーニング）を促す。 授業内では、基本的にはノートPCは利用しないが、予め指示があった場合は、ノートPCやイヤフォン・ヘッドフォンを持参し、利用のこと。",
  "attention": "・指定されたクラスで授業に参加すること。 ・課題は期限内に提出すること。 ・遅刻・欠席は厳禁。 ・配慮検討の対象を満たす欠席の場合は、その証明となるものを添付し所定の欠席届を提出のこと。 (詳細は、授業初回にて説明予定)。",
  "preparation": "課された課題を実施した上で授業に臨むこと(授業ではその振り返りや応用する実践的な練習を行う)。次回の授業に備え、授業中は学んだ英語表現をノートに記録し、授業後に復習すること。授業で学んだ語彙や表現を実際に使い、積極的に英語を使うこと。",
  "evaluation": "「授業参加姿勢 (30%)」「課題点 (30％)」「到達度チェック (40％)」を総合的に評価する。合格点は60％とする。 授業参加姿勢とは、積極的な発言、質問、グループワークやペアワーク等授業内活動に取り組む姿勢や予習・復習状況確認のために実施する小テストの結果に関する評価を含む。 課題に関するフィードバックは、口頭、オンライン掲示、または紙上のいずれかで学生に提供される。",
  "texts": [
    {
      "name": "Marc Helgesen 他著; English Firsthand 1 (5th Edition) Student Book with MyMobileWorld (Pearson); ISBN9789813132771; 3,300円 (税別)",
      "isbn": "9789813132771"
    }
  ],
  "references": [
    {
      "name": "必要に応じて授業内で資料を提供する。",
      "isbn": null
    }
  ],
  "plans": [
    {
      "1": {
        "name": "コース概要、英会話のストラテジーについて",
        "incharge": null
      }
    },
    {
      "2": {
        "name": "Unit 2 人物の描写 (1)",
        "incharge": null
      }
    },
    {
      "3": {
        "name": "Unit 2 人物の描写 (2)",
        "incharge": null
      }
    },
    {
      "4": {
        "name": "Unit 3 日常生活の描写",
        "incharge": null
      }
    },
    {
      "5": {
        "name": "Unit 4 室内の描写",
        "incharge": null
      }
    },
    {
      "6": {
        "name": "Unit 5 道案内",
        "incharge": null
      }
    },
    {
      "7": {
        "name": "復習、学習理解度の確認",
        "incharge": null
      }
    },
    {
      "8": {
        "name": "Presentation Skillsを学ぶ",
        "incharge": null
      }
    },
    {
      "9": {
        "name": "Unit 5 観光",
        "incharge": null
      }
    },
    {
      "10": {
        "name": "Unit 6 過去の出来事 (1)",
        "incharge": null
      }
    },
    {
      "11": {
        "name": "Presentation Skillsの練習",
        "incharge": null
      }
    },
    {
      "12": {
        "name": "Unit 6 過去の出来事 (2)",
        "incharge": null
      }
    },
    {
      "13": {
        "name": "Presentation 発表 (1)",
        "incharge": null
      }
    },
    {
      "14": {
        "name": "Presentation 発表 (2)",
        "incharge": null
      }
    }
  ]
}