{
  "name": "ロボット設計特論",
  "category": "専門科目 サステイナブル工学専攻",
  "type": "講義科目",
  "code": "GE100301",
  "semester": "2026年度 後期",
  "date": "木 2",
  "target": "1年,2年",
  "credit": "1.0",
  "room": "",
  "teachers": [
    {
      "name": "福島 E 文彦",
      "affiliation": "機械工学科"
    }
  ],
  "updated_at": "2026-04-13T17:52:24.268350Z",
  "overview": "サステイナブル社会構築のために、地上・水中・水上・空中などの環境で活躍する高度な知能化ロボットが市販されはじめている。本講義では、各種ロボットの機構設計をはじめ、AI技術を用いた運動生成法の概念を含めた先端的な制御技術について学ぶ。特に地上での移動形態として一般的である車輪・無限軌道型、脚型（ヒューマノイドロボット含め）、節体幹型（ヘビ型、ワーム型）ロボットについて学習し、地雷探査ロボットや各種レスキューロボットの応用事例も含め、ロボット全般について機構・駆動・運動制御系の知識が身につく。",
  "goal": "本授業科目では以下を到達目標とする。 1)目的の機能・仕事を行うためのロボットの形態の選定ができる。 2)ロボットを構成する一般的なアクチュエータ・センサ・制御系の機能と役割を理解できる。 3)AI技術を用いたロボットの運動生成の概念を理解できる。",
  "outcomes": "実学に基づく専門能力、論理的な思考力、分析・評価能力、問題解決力",
  "initiative": "",
  "way": "プロジェクターを使った講義形式の説明が中心となるが、パソコンを使った演習も随時行う【ノートＰＣ必携】。",
  "attention": "ロボットの設計の基礎となる、各学部で履修した関連科目を復習すること。 例： ・機構学、材料力学、機械力学、流体力学、熱工学、電磁気学 ・機械製図実習、３Ｄ－ＣＡＤ実習、機械工学基礎実験 ・サステイナブル工学基礎、サステイナブル工学実習",
  "preparation": "授業前には指定した技術資料や論文を講読してくること。（60分程度） また毎授業後にはレポート等を提出すること。（60分程度）",
  "evaluation": "レポート（60％）と理解度チェック（40％）で総合評価する。",
  "texts": [
    {
      "name": "特になし。",
      "isbn": null
    }
  ],
  "references": [
    {
      "name": "レポート（白書、戦略 等），（一社）日本ロボット工業会 https://www.jara.jp/various/report/index.html NEDOロボット白書2014 https://www.nedo.go.jp/content/100567345.pdf 産業用ロボット白書2017年版 PDF版 https://www.spi-information.com/report/16801.html 注意：目次のみを参考にする 機械設計入門、First Stageシリーズ 塚田 忠夫/舟橋 宏明/野口 昭治【監修】、 実教出版株式会社、 2014年09月初版発行、 ISBN:978-4-407-33541-5",
      "isbn": "9784407335415"
    }
  ],
  "plans": [
    {
      "1": {
        "name": "総論",
        "incharge": null
      }
    },
    {
      "2": {
        "name": "ロボットを構成する機械要素、ロボットの形態",
        "incharge": null
      }
    },
    {
      "3": {
        "name": "ロボットの駆動制御系",
        "incharge": null
      }
    },
    {
      "4": {
        "name": "ロボットのマニピュレーションと把持機構",
        "incharge": null
      }
    },
    {
      "5": {
        "name": "ロボットの移動形態と機構 １",
        "incharge": null
      }
    },
    {
      "6": {
        "name": "ロボットの移動形態と機構 ２",
        "incharge": null
      }
    },
    {
      "7": {
        "name": "ロボットと人工知能（AI)、IoT",
        "incharge": null
      }
    }
  ]
}