{
  "name": "医療科学の基礎I[臨工]",
  "category": "基礎教育科目 自然科学",
  "type": "講義・実験科目",
  "code": "T2820",
  "semester": "2026年度 前期",
  "date": "金 3, 金 4, 金 5",
  "target": "1年,2年,3年,4年",
  "credit": "2.0",
  "room": "Ｍ４０５基礎医学実習室, Ｍ４０７生物・化学実習室",
  "teachers": [
    {
      "name": "都丸 亜希子",
      "affiliation": "兼任講師"
    },
    {
      "name": "下村 美文",
      "affiliation": "臨床工学科"
    },
    {
      "name": "内田 庸助",
      "affiliation": "臨床工学科"
    }
  ],
  "updated_at": "2026-04-13T17:52:21.221806Z",
  "overview": "本授業では、講義と実験を通じて、化学・生物・計量など自然科学の基礎知識と基本的な実験手技について学ぶことを目的とする。これらの内容は、臨床工学技士に必要とされる専門基礎科目の理解に役立つ。また、基本的な実験手技とともにレポートの書き方についても修得する。",
  "goal": "生物・化学・計量に関する基礎的知識を習得する。コミュニケーション能力、論理的な思考力、分析・評価能力、問題解決力の習得を目指す。",
  "outcomes": "コミュニケーション能力、論理的な思考力、分析・評価能力、問題解決力",
  "initiative": "アクティブラーニング",
  "way": "講義では実験の基本的な原理および実験機器の操作方法を解説した後、実験を安全に遂行するための注意事項を説明する。また適宜演習を行う。実験では各操作の意味を十分に理解した上で実験に臨み、実験中は実験ノートに詳細な経過を記録しなければならない。実験は3，4名程度の班単位でグループワークとしてアクティブラーニングを行うが、レポートは各自で作成する。レポートの作成方法は実験テキストを参考にする。皮膚の2点識別実験ではノートPCを使用する。",
  "attention": "実験テキスト、白衣、名札、実験用のノート、A4レポート用紙（罫線）を持参すること。 予習、復習をしっかりと行うこと。",
  "preparation": "配布する実験テキストを熟読し、一つ一つの操作がいかなる原理と目的を有しているかを事前に理解し、実験ノートにまとめる必要がある。また、必要に応じて図書館などを利用して関連事項について各自で調査しておくこと。",
  "evaluation": "実験への取り組み態度（10％）、レポートや演習課題等の提出物（90％）を総合的に判断する。全ての実験に出席して、レポートおよび演習課題を期限内に必ず提出することが必要条件となる。専門基礎科目を学ぶ上で、十分な基礎知識がついたかどうかを評価基準とする。",
  "texts": [
    {
      "name": "クリニカルスタディ（2025年11月臨時増刊号）苦手科目をまとめて攻略！ 基礎から固める国試対策ドリル メヂカルフレンド社 雑誌JAN 4910032281154 実験テキストを配布する。",
      "isbn": null
    }
  ],
  "references": [
    {
      "name": "クリニカルスタディ（2025年5月増刊号）基本が学べる！解剖生理書き込みドリル メヂカルフレンド社 （解剖学の講義でも使用）",
      "isbn": null
    }
  ],
  "plans": [
    {
      "1": {
        "name": "ガイダンス",
        "incharge": null
      }
    },
    {
      "2": {
        "name": "基本的な器具の使用方法",
        "incharge": null
      }
    },
    {
      "3": {
        "name": "皮膚の2点識別実験",
        "incharge": null
      }
    },
    {
      "4": {
        "name": "顕微鏡の基本的な操作方法",
        "incharge": null
      }
    },
    {
      "5": {
        "name": "植物細胞と浸透圧1",
        "incharge": null
      }
    },
    {
      "6": {
        "name": "植物細胞と浸透圧2",
        "incharge": null
      }
    },
    {
      "7": {
        "name": "演習1",
        "incharge": null
      }
    },
    {
      "8": {
        "name": "微生物1（各種の培地の調整）",
        "incharge": null
      }
    },
    {
      "9": {
        "name": "微生物2（身の回りに存在する微生物の観察）",
        "incharge": null
      }
    },
    {
      "10": {
        "name": "微生物3",
        "incharge": null
      }
    },
    {
      "11": {
        "name": "血液の分離と溶血",
        "incharge": null
      }
    },
    {
      "12": {
        "name": "pH変化と緩衝液の働き1",
        "incharge": null
      }
    },
    {
      "13": {
        "name": "pH変化と緩衝液の働き2",
        "incharge": null
      }
    },
    {
      "14": {
        "name": "演習2",
        "incharge": null
      }
    },
    {
      "15": {
        "name": "まとめ",
        "incharge": null
      }
    }
  ]
}